slogs/__init__.py
slogs/slogs.py
slogs/templates.py
slogs-0.1.4.dist-info/METADATA
slogs-0.1.4.dist-info/WHEEL
slogs-0.1.4.dist-info/top_level.txt
slogs-0.1.4.dist-info/RECORD
