Metadata-Version: 2.1
Name: slogs
Version: 0.1.4
Summary: A simple python logs printer
Home-page: https://github.com/deepcaps/
Author: deepcaps
Author-email: deepcaps@outlook.com
Requires-Dist: colorama
